Autofhm/__init__.py
Autofhm/__main__.py
Autofhm/autofhm.py
Autofhm/feature/__init__.py
Autofhm/feature/default_types.py
Autofhm/feature/features.py
Autofhm/feature/scaling.py
Autofhm/feature/transforms.py
Autofhm/ga/__init__.py
Autofhm/ga/config_model.py
Autofhm/ga/ga.py
Autofhm/ga/ga_operators.py
Autofhm/utils/__init__.py
Autofhm/utils/console.py
Autofhm/utils/metrics.py
Autofhm/utils/parse_util.py
Autofhm/utils/utils.py
Autofhm-2.0.6.dist-info/LICENSE
Autofhm-2.0.6.dist-info/METADATA
Autofhm-2.0.6.dist-info/WHEEL
Autofhm-2.0.6.dist-info/top_level.txt
Autofhm-2.0.6.dist-info/RECORD
